actor_au/__init__.py
actor_au/actor_au.py
actor_au-0.0.1a7.dist-info/LICENSE
actor_au-0.0.1a7.dist-info/METADATA
actor_au-0.0.1a7.dist-info/WHEEL
actor_au-0.0.1a7.dist-info/top_level.txt
actor_au-0.0.1a7.dist-info/RECORD
