Metadata-Version: 2.1
Name: actor-au
Version: 0.0.1a7
Summary: A very simple actor simulation framework, intended for use with theatre_au.
Home-page: http://probablytom.com/
Author: Tom Wallis
Author-email: w.wallis.1@research.gla.ac.uk
License: MIT
Platform: UNKNOWN
Classifier: License :: OSI Approved :: MIT License
Classifier: Programming Language :: Python
Classifier: Programming Language :: Python :: 2
Classifier: Programming Language :: Python :: 2.7
Classifier: Programming Language :: Python :: Implementation :: CPython
Classifier: Programming Language :: Python :: Implementation :: PyPy
Requires-Python: <3
